[
	{"id":1, "value": "db thruster", "type": "mainsite", "date": "01/01/2017"},
	{"id":1, "value": "run", "type": "mainsite", "date": "01/01/2017"},
	{"id":1, "value": "row", "type": "mainsite", "date": "03/01/2017"},
	{"id":1, "value": "du", "type": "mainsite", "date": "03/01/2017"},
	{"id":1, "value": "lunge", "type": "mainsite", "date": "03/01/2017"},
	{"id":1, "value": "back squat", "type": "mainsite", "date": "04/01/2017"},
	{"id":1, "value": "strict press", "type": "mainsite", "date": "04/01/2017"},
	{"id":1, "value": "deadlift", "type": "mainsite", "date": "04/01/2017"},
	{"id":1, "value": "wall ball", "type": "mainsite", "date": "05/01/2017"},
	{"id":1, "value": "hspu", "type": "mainsite", "date": "07/01/2017"},
	{"id":1, "value": "rope climb", "type": "mainsite", "date": "07/01/2017"},
	{"id":1, "value": "run", "type": "mainsite", "date": "08/01/2017"},
	{"id":1, "value": "kb swing", "type": "mainsite", "date": "08/01/2017"},
	{"id":1, "value": "pull up", "type": "mainsite", "date": "08/01/2017"},
	{"id":1, "value": "oh squat", "type": "mainsite", "date": "09/01/2017"},
	{"id":1, "value": "squat", "type": "mainsite", "date": "11/01/2017"},
	{"id":1, "value": "push up", "type": "mainsite", "date": "11/01/2017"},
	{"id":1, "value": "pull up", "type": "mainsite", "date": "11/01/2017"},
	{"id":1, "value": "ghd", "type": "mainsite", "date": "12/01/2017"},
	{"id":1, "value": "oh lunge", "type": "mainsite", "date": "12/01/2017"},
	{"id":1, "value": "deadlift", "type": "mainsite", "date": "13/01/2017"},
	{"id":1, "value": "bench", "type": "mainsite", "date": "13/01/2017"},
	{"id":1, "value": "clean", "type": "mainsite", "date": "13/01/2017"},
	{"id":1, "value": "box jump", "type": "mainsite", "date": "15/01/2017"},
	{"id":1, "value": "pull up", "type": "mainsite", "date": "15/01/2017"},
	{"id":1, "value": "kb swing", "type": "mainsite", "date": "15/01/2017"},
	{"id":1, "value": "lunge", "type": "mainsite", "date": "15/01/2017"},
	{"id":1, "value": "kte", "type": "mainsite", "date": "15/01/2017"},
	{"id":1, "value": "push press", "type": "mainsite", "date": "15/01/2017"},
	{"id":1, "value": "back extension", "type": "mainsite", "date": "15/01/2017"},
	{"id":1, "value": "wall ball", "type": "mainsite", "date": "15/01/2017"},
	{"id":1, "value": "burpee", "type": "mainsite", "date": "15/01/2017"},
	{"id":1, "value": "du", "type": "mainsite", "date": "15/01/2017"},
	{"id":1, "value": "run", "type": "mainsite", "date": "16/01/2017"},
	{"id":1, "value": "oh squat", "type": "mainsite", "date": "16/01/2017"},
	{"id":1, "value": "sdhp", "type": "mainsite", "date": "16/01/2017"},
	{"id":1, "value": "power clean", "type": "mainsite", "date": "17/01/2017"},
	{"id":1, "value": "run", "type": "mainsite", "date": "19/01/2017"},
	{"id":1, "value": "kb swing", "type": "mainsite", "date": "19/01/2017"},
	{"id":1, "value": "burpee", "type": "mainsite", "date": "19/01/2017"},
	{"id":1, "value": "box jump", "type": "mainsite", "date": "19/01/2017"},
	{"id":1, "value": "thruster", "type": "mainsite", "date": "20/01/2017"},
	{"id":1, "value": "ring mu", "type": "mainsite", "date": "20/01/2017"},
	{"id":1, "value": "snatch balance", "type": "mainsite", "date": "21/01/2017"},
	{"id":1, "value": "burpee", "type": "mainsite", "date": "23/01/2017"},
	{"id":1, "value": "back squat", "type": "mainsite", "date": "23/01/2017"},
	{"id":1, "value": "strict press", "type": "mainsite", "date": "23/01/2017"},
	{"id":1, "value": "deadlift", "type": "mainsite", "date": "23/01/2017"},
	{"id":1, "value": "L pull up", "type": "mainsite", "date": "24/01/2017"},
	{"id":1, "value": "hs walk", "type": "mainsite", "date": "24/01/2017"},
	{"id":1, "value": "pull up", "type": "mainsite", "date": "24/01/2017"},
	{"id":1, "value": "hs hold", "type": "mainsite", "date": "24/01/2017"},
	{"id":1, "value": "run", "type": "mainsite", "date": "25/01/2017"},
	{"id":1, "value": "power snatch", "type": "mainsite", "date": "27/01/2017"},
	{"id":1, "value": "du", "type": "mainsite", "date": "27/01/2017"},
	{"id":1, "value": "row", "type": "mainsite", "date": "28/01/2017"},
	{"id":1, "value": "farmer walk", "type": "mainsite", "date": "28/01/2017"},
	{"id":1, "value": "waiter walk", "type": "mainsite", "date": "28/01/2017"},
	{"id":1, "value": "ttb", "type": "mainsite", "date": "29/01/2017"},
	{"id":1, "value": "wall ball", "type": "mainsite", "date": "29/01/2017"},
	{"id":1, "value": "thruster", "type": "mainsite", "date": "29/01/2017"},
	{"id":1, "value": "front squat", "type": "mainsite", "date": "31/01/2017"},
	{"id":1, "value": "box jump", "type": "mainsite", "date": "31/01/2017"},
	{"id":1, "value": "row", "type": "mainsite", "date": "31/01/2017"},
	{"id":1, "value": "push press", "type": "mainsite", "date": "01/02/2017"},
	{"id":1, "value": "squat clean", "type": "mainsite", "date": "02/02/2017"},
	{"id":1, "value": "pull up", "type": "mainsite", "date": "02/02/2017"},
	{"id":1, "value": "run", "type": "mainsite", "date": "02/02/2017"},
	{"id":1, "value": "snatch", "type": "mainsite", "date": "04/02/2017"},
	{"id":1, "value": "back squat", "type": "mainsite", "date": "05/02/2017"},
	{"id":1, "value": "row", "type": "mainsite", "date": "06/02/2017"},
	{"id":1, "value": "turkish get up", "type": "mainsite", "date": "06/02/2017"},
	{"id":1, "value": "thruster", "type": "mainsite", "date": "08/02/2017"},
	{"id":1, "value": "pull up", "type": "mainsite", "date": "08/02/2017"},
	{"id":1, "value": "run", "type": "mainsite", "date": "08/02/2017"},
	{"id":1, "value": "hspu", "type": "mainsite", "date": "09/02/2017"},
	{"id":1, "value": "clean", "type": "mainsite", "date": "09/02/2017"},
	{"id":1, "value": "lunge", "type": "mainsite", "date": "10/02/2017"},
	{"id":1, "value": "c2b", "type": "mainsite", "date": "10/02/2017"},
	{"id":1, "value": "box jump", "type": "mainsite", "date": "10/02/2017"},
	{"id":1, "value": "tu", "type": "mainsite", "date": "10/02/2017"},
	{"id":1, "value": "back extension", "type": "mainsite", "date": "10/02/2017"},
	{"id":1, "value": "ring dip", "type": "mainsite", "date": "10/02/2017"},
	{"id":1, "value": "kte", "type": "mainsite", "date": "10/02/2017"},
	{"id":1, "value": "wall ball", "type": "mainsite", "date": "10/02/2017"},
	{"id":1, "value": "sit up", "type": "mainsite", "date": "10/02/2017"},
	{"id":1, "value": "rope climb", "type": "mainsite", "date": "10/02/2017"},
	{"id":1, "value": "du", "type": "mainsite", "date": "12/02/2017"},
	{"id":1, "value": "front squat", "type": "mainsite", "date": "12/02/2017"},
	{"id":1, "value": "deadlift", "type": "mainsite", "date": "13/02/2017"},
	{"id":1, "value": "push up", "type": "mainsite", "date": "13/02/2017"},
	{"id":1, "value": "box jump", "type": "mainsite", "date": "13/02/2017"},
	{"id":1, "value": "ttb", "type": "mainsite", "date": "14/02/2017"},
	{"id":1, "value": "ring dip", "type": "mainsite", "date": "14/02/2017"},
	{"id":1, "value": "broad jump", "type": "mainsite", "date": "14/02/2017"},
	{"id":1, "value": "row", "type": "mainsite", "date": "14/02/2017"},
	{"id":1, "value": "btn jerk", "type": "mainsite", "date": "16/02/2017"},
	{"id":1, "value": "push jerk", "type": "mainsite", "date": "16/02/2017"},
	{"id":1, "value": "power snatch", "type": "mainsite", "date": "17/02/2017"},
	{"id":1, "value": "bar mu", "type": "mainsite", "date": "17/02/2017"},
	{"id":1, "value": "deadlift", "type": "mainsite", "date": "18/02/2017"},
	{"id":1, "value": "hang power clean", "type": "mainsite", "date": "18/02/2017"},
	{"id":1, "value": "front squat", "type": "mainsite", "date": "18/02/2017"},
	{"id":1, "value": "push press", "type": "mainsite", "date": "18/02/2017"},
	{"id":1, "value": "ghd", "type": "mainsite", "date": "20/02/2017"},
	{"id":1, "value": "cluster", "type": "mainsite", "date": "20/02/2017"},
	{"id":1, "value": "pull up", "type": "mainsite", "date": "21/02/2017"},
	{"id":1, "value": "ring mu", "type": "mainsite", "date": "21/02/2017"},
	{"id":1, "value": "run", "type": "mainsite", "date": "21/02/2017"},
	{"id":1, "value": "hspu", "type": "mainsite", "date": "22/02/2017"},
	{"id":1, "value": "row", "type": "mainsite", "date": "22/02/2017"},
	{"id":1, "value": "pistol squat", "type": "mainsite", "date": "22/02/2017"},
	{"id":1, "value": "db snatch", "type": "mainsite", "date": "24/02/2017"},
	{"id":1, "value": "burpee", "type": "mainsite", "date": "24/02/2017"},
	{"id":1, "value": "box jump", "type": "mainsite", "date": "24/02/2017"},
	{"id":1, "value": "front squat", "type": "mainsite", "date": "25/02/2017"},
	{"id":1, "value": "run", "type": "mainsite", "date": "25/02/2017"},
	{"id":1, "value": "rope climb", "type": "mainsite", "date": "26/02/2017"},
	{"id":1, "value": "push press", "type": "mainsite", "date": "26/02/2017"},
	{"id":1, "value": "du", "type": "mainsite", "date": "26/02/2017"},
	{"id":1, "value": "power clean", "type": "mainsite", "date": "28/02/2017"},
	{"id":1, "value": "push up", "type": "mainsite", "date": "28/02/2017"},
	{"id":1, "value": "row", "type": "mainsite", "date": "01/03/2017"},
	{"id":1, "value": "oh squat", "type": "mainsite", "date": "02/03/2017"},
	{"id":1, "value": "lunge", "type": "mainsite", "date": "03/03/2017"},
	{"id":1, "value": "ttb", "type": "mainsite", "date": "03/03/2017"},
	{"id":1, "value": "db clean", "type": "mainsite", "date": "03/03/2017"},
	{"id":1, "value": "bar mu", "type": "mainsite", "date": "03/03/2017"},
	{"id":1, "value": "hs walk", "type": "mainsite", "date": "05/03/2017"},
	{"id":1, "value": "pistol squat", "type": "mainsite", "date": "05/03/2017"},
	{"id":1, "value": "ring dip", "type": "mainsite", "date": "06/03/2017"},
	{"id":1, "value": "ghd", "type": "mainsite", "date": "06/03/2017"},
	{"id":1, "value": "run", "type": "mainsite", "date": "06/03/2017"},
	{"id":1, "value": "deadlift", "type": "mainsite", "date": "08/03/2017"},
	{"id":1, "value": "run", "type": "mainsite", "date": "09/03/2017"},
	{"id":1, "value": "c2b", "type": "mainsite", "date": "10/03/2017"},
	{"id":1, "value": "squat snatch", "type": "mainsite", "date": "10/03/2017"},
	{"id":1, "value": "row", "type": "mainsite", "date": "12/03/2017"},
	{"id":1, "value": "bench", "type": "mainsite", "date": "12/03/2017"},
	{"id":1, "value": "legless rope climb", "type": "mainsite", "date": "13/03/2017"},
	{"id":1, "value": "push jerk", "type": "mainsite", "date": "13/03/2017"},
	{"id":1, "value": "deadlift", "type": "mainsite", "date": "13/03/2017"},
	{"id":1, "value": "ghd", "type": "mainsite", "date": "13/03/2017"},
	{"id":1, "value": "wall ball", "type": "mainsite", "date": "13/03/2017"},
	{"id":1, "value": "back squat", "type": "mainsite", "date": "14/03/2017"},
	{"id":1, "value": "kb c&j", "type": "mainsite", "date": "16/03/2017"},
	{"id":1, "value": "ring mu", "type": "mainsite", "date": "16/03/2017"},
	{"id":1, "value": "deadlift", "type": "mainsite", "date": "17/03/2017"},
	{"id":1, "value": "wall ball", "type": "mainsite", "date": "17/03/2017"},
	{"id":1, "value": "row", "type": "mainsite", "date": "17/03/2017"},
	{"id":1, "value": "hspu", "type": "mainsite", "date": "17/03/2017"},
	{"id":1, "value": "front squat", "type": "mainsite", "date": "18/03/2017"},
	{"id":1, "value": "thruster", "type": "mainsite", "date": "18/03/2017"},
	{"id":1, "value": "push jerk", "type": "mainsite", "date": "18/03/2017"},
	{"id":1, "value": "ghd", "type": "mainsite", "date": "20/03/2017"},
	{"id":1, "value": "hs walk", "type": "mainsite", "date": "20/03/2017"},
	{"id":1, "value": "oh lunge", "type": "mainsite", "date": "20/03/2017"},
	{"id":1, "value": "run", "type": "mainsite", "date": "21/03/2017"},
	{"id":1, "value": "ttb", "type": "mainsite", "date": "21/03/2017"},
	{"id":1, "value": "front squat", "type": "mainsite", "date": "21/03/2017"},
	{"id":1, "value": "rope climb", "type": "mainsite", "date": "21/03/2017"},
	{"id":1, "value": "pull up", "type": "mainsite", "date": "22/03/2017"},
	{"id":1, "value": "row", "type": "mainsite", "date": "22/03/2017"},
	{"id":1, "value": "thruster", "type": "mainsite", "date": "24/03/2017"},
	{"id":1, "value": "du", "type": "mainsite", "date": "24/03/2017"},
	{"id":1, "value": "run", "type": "mainsite", "date": "25/03/2017"},
	{"id":1, "value": "back squat", "type": "mainsite", "date": "26/03/2017"},
	{"id":1, "value": "c2b", "type": "mainsite", "date": "26/03/2017"},
	{"id":1, "value": "power clean", "type": "mainsite", "date": "26/03/2017"},
	{"id":1, "value": "mb clean", "type": "mainsite", "date": "28/03/2017"},
	{"id":1, "value": "push jerk", "type": "mainsite", "date": "28/03/2017"},
	{"id":1, "value": "run", "type": "mainsite", "date": "29/03/2017"},
	{"id":1, "value": "deadlift", "type": "mainsite", "date": "29/03/2017"},
	{"id":1, "value": "ring mu", "type": "mainsite", "date": "30/03/2017"},
	{"id":1, "value": "squat snatch", "type": "mainsite", "date": "30/03/2017"},
	{"id":1, "value": "c&j", "type": "mainsite", "date": "01/04/2017"},
	{"id":1, "value": "hspu", "type": "mainsite", "date": "02/04/2017"},
	{"id":1, "value": "lunge", "type": "mainsite", "date": "02/04/2017"},
	{"id":1, "value": "burpee", "type": "mainsite", "date": "03/04/2017"},
	{"id":1, "value": "front squat", "type": "mainsite", "date": "03/04/2017"},
	{"id":1, "value": "c2b", "type": "mainsite", "date": "03/04/2017"},
	{"id":1, "value": "ghd", "type": "mainsite", "date": "05/04/2017"},
	{"id":1, "value": "db push jerk", "type": "mainsite", "date": "05/04/2017"},
	{"id":1, "value": "deadlift", "type": "mainsite", "date": "06/04/2017"},
	{"id":1, "value": "run", "type": "mainsite", "date": "07/04/2017"},
	{"id":1, "value": "L pull up", "type": "mainsite", "date": "07/04/2017"},
	{"id":1, "value": "hip extension", "type": "mainsite", "date": "07/04/2017"},
	{"id":1, "value": "db thruster", "type": "mainsite", "date": "09/04/2017"},
	{"id":1, "value": "ttb", "type": "mainsite", "date": "09/04/2017"},
	{"id":1, "value": "box jump", "type": "mainsite", "date": "10/04/2017"},
	{"id":1, "value": "run", "type": "mainsite", "date": "10/04/2017"},
	{"id":1, "value": "c&j", "type": "mainsite", "date": "11/04/2017"},
	{"id":1, "value": "bar mu", "type": "mainsite", "date": "11/04/2017"},
	{"id":1, "value": "hs walk", "type": "mainsite", "date": "11/04/2017"},
	{"id":1, "value": "back squat", "type": "mainsite", "date": "13/04/2017"},
	{"id":1, "value": "row", "type": "mainsite", "date": "14/04/2017"},
	{"id":1, "value": "run", "type": "mainsite", "date": "15/04/2017"},
	{"id":1, "value": "pull up", "type": "mainsite", "date": "15/04/2017"},
	{"id":1, "value": "burpee", "type": "mainsite", "date": "15/04/2017"},
	{"id":1, "value": "box jump", "type": "mainsite", "date": "15/04/2017"},
	{"id":1, "value": "clean", "type": "mainsite", "date": "15/04/2017"},
	{"id":1, "value": "rope climb", "type": "mainsite", "date": "17/04/2017"},
	{"id":1, "value": "thruster", "type": "mainsite", "date": "18/04/2017"},
	{"id":1, "value": "sdhp", "type": "mainsite", "date": "18/04/2017"},
	{"id":1, "value": "snatch", "type": "mainsite", "date": "19/04/2017"},
	{"id":1, "value": "db snatch", "type": "mainsite", "date": "21/04/2017"},
	{"id":1, "value": "row", "type": "mainsite", "date": "21/04/2017"},
	{"id":1, "value": "burpee", "type": "mainsite", "date": "21/04/2017"},
	{"id":1, "value": "bar mu", "type": "mainsite", "date": "21/04/2017"},
	{"id":1, "value": "ttb", "type": "mainsite", "date": "22/04/2017"},
	{"id":1, "value": "du", "type": "mainsite", "date": "22/04/2017"},
	{"id":1, "value": "squat clean", "type": "mainsite", "date": "22/04/2017"},
	{"id":1, "value": "push jerk", "type": "mainsite", "date": "23/04/2017"},
	{"id":1, "value": "c2b", "type": "mainsite", "date": "23/04/2017"},
	{"id":1, "value": "deadlift", "type": "mainsite", "date": "25/04/2017"},
	{"id":1, "value": "hspu", "type": "mainsite", "date": "25/04/2017"},
	{"id":1, "value": "front squat", "type": "mainsite", "date": "25/04/2017"},
	{"id":1, "value": "du", "type": "mainsite", "date": "26/04/2017"},
	{"id":1, "value": "sit up", "type": "mainsite", "date": "26/04/2017"},
	{"id":1, "value": "thruster", "type": "mainsite", "date": "27/04/2017"},
	{"id":1, "value": "db squat clean", "type": "mainsite", "date": "29/04/2017"},
	{"id":1, "value": "pull up", "type": "mainsite", "date": "29/04/2017"},
	{"id":1, "value": "box jump", "type": "mainsite", "date": "29/04/2017"},
	{"id":1, "value": "run", "type": "mainsite", "date": "30/04/2017"},
	{"id":1, "value": "back squat", "type": "mainsite", "date": "30/04/2017"},
	{"id":1, "value": "deadlift", "type": "mainsite", "date": "30/04/2017"},
	{"id":1, "value": "strict press", "type": "mainsite", "date": "01/05/2017"},
	{"id":1, "value": "back extension", "type": "mainsite", "date": "01/05/2017"},
	{"id":1, "value": "hang squat snatch", "type": "mainsite", "date": "03/05/2017"},
	{"id":1, "value": "push press", "type": "mainsite", "date": "04/05/2017"},
	{"id":1, "value": "rope climb", "type": "mainsite", "date": "04/05/2017"},
	{"id":1, "value": "wall ball", "type": "mainsite", "date": "05/05/2017"},
	{"id":1, "value": "box jump", "type": "mainsite", "date": "05/05/2017"},
	{"id":1, "value": "thruster", "type": "mainsite", "date": "07/05/2017"},
	{"id":1, "value": "pull up", "type": "mainsite", "date": "07/05/2017"},
	{"id":1, "value": "burpee", "type": "mainsite", "date": "07/05/2017"},
	{"id":1, "value": "run", "type": "mainsite", "date": "08/05/2017"},
	{"id":1, "value": "hs walk", "type": "mainsite", "date": "08/05/2017"},
	{"id":1, "value": "hs hold", "type": "mainsite", "date": "08/05/2017"},
	{"id":1, "value": "su", "type": "mainsite", "date": "09/05/2017"},
	{"id":1, "value": "bar mu", "type": "mainsite", "date": "09/05/2017"},
	{"id":1, "value": "squat clean", "type": "mainsite", "date": "09/05/2017"},
	{"id":1, "value": "db snatch", "type": "mainsite", "date": "11/05/2017"},
	{"id":1, "value": "ring dip", "type": "mainsite", "date": "11/05/2017"},
	{"id":1, "value": "run", "type": "mainsite", "date": "12/05/2017"},
	{"id":1, "value": "ghd", "type": "mainsite", "date": "12/05/2017"},
	{"id":1, "value": "oh squat", "type": "mainsite", "date": "12/05/2017"},
	{"id":1, "value": "sumo deadlift", "type": "mainsite", "date": "13/05/2017"},
	{"id":1, "value": "bench", "type": "mainsite", "date": "13/05/2017"},
	{"id":1, "value": "oh lunge", "type": "mainsite", "date": "15/05/2017"},
	{"id":1, "value": "du", "type": "mainsite", "date": "15/05/2017"},
	{"id":1, "value": "wall ball", "type": "mainsite", "date": "15/05/2017"},
	{"id":1, "value": "rope climb", "type": "mainsite", "date": "15/05/2017"},
	{"id":1, "value": "row", "type": "mainsite", "date": "16/05/2017"},
	{"id":1, "value": "run", "type": "mainsite", "date": "17/05/2017"},
	{"id":1, "value": "oh squat", "type": "mainsite", "date": "17/05/2017"},
	{"id":1, "value": "run", "type": "mainsite", "date": "19/05/2017"},
	{"id":1, "value": "hspu", "type": "mainsite", "date": "19/05/2017"},
	{"id":1, "value": "c2b", "type": "mainsite", "date": "19/05/2017"},
	{"id":1, "value": "squat", "type": "mainsite", "date": "19/05/2017"},
	{"id":1, "value": "hs walk", "type": "mainsite", "date": "20/05/2017"},
	{"id":1, "value": "kb deadlift", "type": "mainsite", "date": "20/05/2017"},
	{"id":1, "value": "ttb", "type": "mainsite", "date": "20/05/2017"},
	{"id":1, "value": "row", "type": "mainsite", "date": "21/05/2017"},
	{"id":1, "value": "squat snatch", "type": "mainsite", "date": "21/05/2017"},
	{"id":1, "value": "push up", "type": "mainsite", "date": "21/05/2017"},
	{"id":1, "value": "hang squat clean", "type": "mainsite", "date": "23/05/2017"},
	{"id":1, "value": "front squat", "type": "mainsite", "date": "23/05/2017"},
	{"id":1, "value": "split jerk", "type": "mainsite", "date": "23/05/2017"},
	{"id":1, "value": "ring mu", "type": "mainsite", "date": "24/05/2017"},
	{"id":1, "value": "oh squat", "type": "mainsite", "date": "24/05/2017"},
	{"id":1, "value": "pistol squat", "type": "mainsite", "date": "25/05/2017"},
	{"id":1, "value": "ghd", "type": "mainsite", "date": "25/05/2017"},
	{"id":1, "value": "hspu", "type": "mainsite", "date": "27/05/2017"},
	{"id":1, "value": "L rope climb", "type": "mainsite", "date": "27/05/2017"},
	{"id":1, "value": "bike", "type": "mainsite", "date": "28/05/2017"},
	{"id":1, "value": "burpee", "type": "mainsite", "date": "28/05/2017"},
	{"id":1, "value": "box jump", "type": "mainsite", "date": "28/05/2017"},
	{"id":1, "value": "clean", "type": "mainsite", "date": "28/05/2017"},
	{"id":1, "value": "pull up", "type": "mainsite", "date": "29/05/2017"},
	{"id":1, "value": "lunge", "type": "mainsite", "date": "29/05/2017"},
	{"id":1, "value": "push up", "type": "mainsite", "date": "29/05/2017"},
	{"id":1, "value": "deadlift", "type": "mainsite", "date": "31/05/2017"},
	{"id":1, "value": "strict press", "type": "mainsite", "date": "31/05/2017"},
	{"id":1, "value": "run", "type": "mainsite", "date": "01/06/2017"},
	{"id":1, "value": "c&j", "type": "mainsite", "date": "02/06/2017"},
	{"id":1, "value": "sdhp", "type": "mainsite", "date": "04/06/2017"},
	{"id":1, "value": "push press", "type": "mainsite", "date": "04/06/2017"},
	{"id":1, "value": "row", "type": "mainsite", "date": "04/06/2017"},
	{"id":1, "value": "hang squat clean", "type": "mainsite", "date": "05/06/2017"},
	{"id":1, "value": "hspu", "type": "mainsite", "date": "05/06/2017"},
	{"id":1, "value": "c&j", "type": "mainsite", "date": "06/06/2017"},
	{"id":1, "value": "thruster", "type": "mainsite", "date": "08/06/2017"},
	{"id":1, "value": "run", "type": "mainsite", "date": "08/06/2017"},
	{"id":1, "value": "c2b", "type": "mainsite", "date": "08/06/2017"},
	{"id":1, "value": "back squat", "type": "mainsite", "date": "09/06/2017"},
	{"id":1, "value": "box jump", "type": "mainsite", "date": "10/06/2017"},
	{"id":1, "value": "wall ball", "type": "mainsite", "date": "10/06/2017"},
	{"id":1, "value": "row", "type": "mainsite", "date": "10/06/2017"},
	{"id":1, "value": "push up", "type": "mainsite", "date": "12/06/2017"},
	{"id":1, "value": "front squat", "type": "mainsite", "date": "12/06/2017"},
	{"id":1, "value": "push press", "type": "mainsite", "date": "12/06/2017"},
	{"id":1, "value": "ghd", "type": "mainsite", "date": "12/06/2017"},
	{"id":1, "value": "broad jump", "type": "mainsite", "date": "13/06/2017"},
	{"id":1, "value": "pull up", "type": "mainsite", "date": "13/06/2017"},
	{"id":1, "value": "hspu", "type": "mainsite", "date": "13/06/2017"},
	{"id":1, "value": "du", "type": "mainsite", "date": "14/06/2017"},
	{"id":1, "value": "db snatch", "type": "mainsite", "date": "14/06/2017"},
	{"id":1, "value": "deadlift", "type": "mainsite", "date": "16/06/2017"},
	{"id":1, "value": "wall ball", "type": "mainsite", "date": "16/06/2017"},
	{"id":1, "value": "burpee", "type": "mainsite", "date": "16/06/2017"},
	{"id":1, "value": "strict press", "type": "mainsite", "date": "17/06/2017"},
	{"id":1, "value": "push press", "type": "mainsite", "date": "17/06/2017"},
	{"id":1, "value": "push jerk", "type": "mainsite", "date": "17/06/2017"},
	{"id":1, "value": "kb swing", "type": "mainsite", "date": "18/06/2017"},
	{"id":1, "value": "tu", "type": "mainsite", "date": "18/06/2017"},
	{"id":1, "value": "run", "type": "mainsite", "date": "18/06/2017"},
	{"id":1, "value": "squat", "type": "mainsite", "date": "20/06/2017"},
	{"id":1, "value": "ring dip", "type": "mainsite", "date": "20/06/2017"},
	{"id":1, "value": "wall ball", "type": "mainsite", "date": "21/06/2017"},
	{"id":1, "value": "pull up", "type": "mainsite", "date": "21/06/2017"},
	{"id":1, "value": "row", "type": "mainsite", "date": "22/06/2017"},
	{"id":1, "value": "power snatch", "type": "mainsite", "date": "22/06/2017"},
	{"id":1, "value": "burpee", "type": "mainsite", "date": "22/06/2017"},
	{"id":1, "value": "run", "type": "mainsite", "date": "24/06/2017"},
	{"id":1, "value": "deadlift", "type": "mainsite", "date": "24/06/2017"},
	{"id":1, "value": "sit up", "type": "mainsite", "date": "24/06/2017"},
	{"id":1, "value": "front squat", "type": "mainsite", "date": "25/06/2017"},
	{"id":1, "value": "L pull up", "type": "mainsite", "date": "26/06/2017"},
	{"id":1, "value": "hspu", "type": "mainsite", "date": "26/06/2017"},
	{"id":1, "value": "hip extension", "type": "mainsite", "date": "26/06/2017"},
	{"id":1, "value": "db deadlift", "type": "mainsite", "date": "28/06/2017"},
	{"id":1, "value": "burpee", "type": "mainsite", "date": "28/06/2017"},
	{"id":1, "value": "db power clean", "type": "mainsite", "date": "28/06/2017"},
	{"id":1, "value": "rope climb", "type": "mainsite", "date": "29/06/2017"},
	{"id":1, "value": "ttb", "type": "mainsite", "date": "29/06/2017"},
	{"id":1, "value": "oh lunge", "type": "mainsite", "date": "29/06/2017"},
	{"id":1, "value": "run", "type": "mainsite", "date": "29/06/2017"},
	{"id":1, "value": "pull up", "type": "mainsite", "date": "30/06/2017"},
	{"id":1, "value": "push up", "type": "mainsite", "date": "30/06/2017"},
	{"id":1, "value": "sit up", "type": "mainsite", "date": "30/06/2017"},
	{"id":1, "value": "squat", "type": "mainsite", "date": "30/06/2017"},
	{"id":1, "value": "swim", "type": "mainsite", "date": "02/07/2017"},
	{"id":1, "value": "back extension", "type": "mainsite", "date": "03/07/2017"},
	{"id":1, "value": "wall ball", "type": "mainsite", "date": "03/07/2017"},
	{"id":1, "value": "squat snatch", "type": "mainsite", "date": "04/07/2017"},
	{"id":1, "value": "pull up", "type": "mainsite", "date": "04/07/2017"},
	{"id":1, "value": "run", "type": "mainsite", "date": "04/07/2017"},
	{"id":1, "value": "squat clean", "type": "mainsite", "date": "04/07/2017"},
	{"id":1, "value": "bench", "type": "mainsite", "date": "06/07/2017"},
	{"id":1, "value": "run", "type": "mainsite", "date": "07/07/2017"},
	{"id":1, "value": "burpee", "type": "mainsite", "date": "08/07/2017"},
	{"id":1, "value": "deadlift", "type": "mainsite", "date": "08/07/2017"},
	{"id":1, "value": "box jump", "type": "mainsite", "date": "08/07/2017"},
	{"id":1, "value": "turkish get up", "type": "mainsite", "date": "08/07/2017"},
	{"id":1, "value": "snatch", "type": "mainsite", "date": "08/07/2017"},
	{"id":1, "value": "push up", "type": "mainsite", "date": "08/07/2017"},
	{"id":1, "value": "row", "type": "mainsite", "date": "08/07/2017"},
	{"id":1, "value": "oh squat", "type": "mainsite", "date": "10/07/2017"},
	{"id":1, "value": "front squat", "type": "mainsite", "date": "10/07/2017"},
	{"id":1, "value": "squat", "type": "mainsite", "date": "10/07/2017"},
	{"id":1, "value": "ring mu", "type": "mainsite", "date": "11/07/2017"},
	{"id":1, "value": "du", "type": "mainsite", "date": "11/07/2017"},
	{"id":1, "value": "hang power clean", "type": "mainsite", "date": "12/07/2017"},
	{"id":1, "value": "hang power snatch", "type": "mainsite", "date": "12/07/2017"},
	{"id":1, "value": "push jerk", "type": "mainsite", "date": "12/07/2017"},
	{"id":1, "value": "box jump", "type": "mainsite", "date": "14/07/2017"},
	{"id":1, "value": "kb swing", "type": "mainsite", "date": "14/07/2017"},
	{"id":1, "value": "kte", "type": "mainsite", "date": "14/07/2017"},
	{"id":1, "value": "wall ball", "type": "mainsite", "date": "14/07/2017"},
	{"id":1, "value": "burpee", "type": "mainsite", "date": "14/07/2017"},
	{"id":1, "value": "squat clean", "type": "mainsite", "date": "15/07/2017"},
	{"id":1, "value": "ring dip", "type": "mainsite", "date": "15/07/2017"},
	{"id":1, "value": "jumping lunge", "type": "mainsite", "date": "16/07/2017"},
	{"id":1, "value": "pull up", "type": "mainsite", "date": "16/07/2017"},
	{"id":1, "value": "push press", "type": "mainsite", "date": "16/07/2017"},
	{"id":1, "value": "hip extension", "type": "mainsite", "date": "16/07/2017"},
	{"id":1, "value": "burpee", "type": "mainsite", "date": "16/07/2017"},
	{"id":1, "value": "snatch balance", "type": "mainsite", "date": "18/07/2017"},
	{"id":1, "value": "ghd", "type": "mainsite", "date": "19/07/2017"},
	{"id":1, "value": "rope climb", "type": "mainsite", "date": "19/07/2017"},
	{"id":1, "value": "run", "type": "mainsite", "date": "19/07/2017"},
	{"id":1, "value": "squat", "type": "mainsite", "date": "20/07/2017"},
	{"id":1, "value": "hspu", "type": "mainsite", "date": "20/07/2017"},
	{"id":1, "value": "deadlift", "type": "mainsite", "date": "20/07/2017"},
	{"id":1, "value": "swim", "type": "mainsite", "date": "22/07/2017"},
	{"id":1, "value": "deadlift", "type": "mainsite", "date": "23/07/2017"},
	{"id":1, "value": "du", "type": "mainsite", "date": "24/07/2017"},
	{"id":1, "value": "oh squat", "type": "mainsite", "date": "24/07/2017"},
	{"id":1, "value": "ring mu", "type": "mainsite", "date": "26/07/2017"},
	{"id":1, "value": "med ball clean", "type": "mainsite", "date": "26/07/2017"},
	{"id":1, "value": "farmer walk", "type": "mainsite", "date": "27/07/2017"},
	{"id":1, "value": "push up", "type": "mainsite", "date": "27/07/2017"},
	{"id":1, "value": "db push jerk", "type": "mainsite", "date": "27/07/2017"},
	{"id":1, "value": "run", "type": "mainsite", "date": "28/07/2017"},
	{"id":1, "value": "L pull up", "type": "mainsite", "date": "28/07/2017"},
	{"id":1, "value": "hip extension", "type": "mainsite", "date": "28/07/2017"},
	{"id":1, "value": "front squat", "type": "mainsite", "date": "30/07/2017"},
	{"id":1, "value": "row", "type": "mainsite", "date": "31/07/2017"},
	{"id":1, "value": "hspu", "type": "mainsite", "date": "31/07/2017"},
	{"id":1, "value": "rope climb", "type": "mainsite", "date": "31/07/2017"},
	{"id":1, "value": "snatch", "type": "mainsite", "date": "01/08/2017"},
	{"id":1, "value": "run", "type": "mainsite", "date": "03/08/2017"},
	{"id":1, "value": "swim", "type": "mainsite", "date": "03/08/2017"},
	{"id":1, "value": "ring mu", "type": "mainsite", "date": "04/08/2017"},
	{"id":1, "value": "snatch", "type": "mainsite", "date": "04/08/2017"},
	{"id":1, "value": "pull up", "type": "mainsite", "date": "05/08/2017"},
	{"id":1, "value": "ghd", "type": "mainsite", "date": "05/08/2017"},
	{"id":1, "value": "pistol squat", "type": "mainsite", "date": "05/08/2017"},
	{"id":1, "value": "row", "type": "mainsite", "date": "05/08/2017"},
	{"id":1, "value": "push press", "type": "mainsite", "date": "05/08/2017"},
	{"id":1, "value": "thruster", "type": "mainsite", "date": "07/08/2017"},
	{"id":1, "value": "du", "type": "mainsite", "date": "07/08/2017"},
	{"id":1, "value": "run", "type": "mainsite", "date": "08/08/2017"},
	{"id":1, "value": "kb snatch", "type": "mainsite", "date": "09/08/2017"},
	{"id":1, "value": "deadlift", "type": "mainsite", "date": "09/08/2017"},
	{"id":1, "value": "box jump", "type": "mainsite", "date": "11/08/2017"},
	{"id":1, "value": "ghd", "type": "mainsite", "date": "11/08/2017"},
	{"id":1, "value": "hspu", "type": "mainsite", "date": "12/08/2017"},
	{"id":1, "value": "pistol squat", "type": "mainsite", "date": "12/08/2017"},
	{"id":1, "value": "pull up", "type": "mainsite", "date": "12/08/2017"},
	{"id":1, "value": "hang power snatch", "type": "mainsite", "date": "13/08/2017"},
	{"id":1, "value": "push press", "type": "mainsite", "date": "15/08/2017"},
	{"id":1, "value": "row", "type": "mainsite", "date": "15/08/2017"},
	{"id":1, "value": "du", "type": "mainsite", "date": "15/08/2017"},
	{"id":1, "value": "pull up", "type": "mainsite", "date": "16/08/2017"},
	{"id":1, "value": "run", "type": "mainsite", "date": "16/08/2017"},
	{"id":1, "value": "squat", "type": "mainsite", "date": "17/08/2017"},
	{"id":1, "value": "swim", "type": "mainsite", "date": "19/08/2017"},
	{"id":1, "value": "db c&j", "type": "mainsite", "date": "19/08/2017"},
	{"id":1, "value": "front squat", "type": "mainsite", "date": "20/08/2017"},
	{"id":1, "value": "med-ball ghd", "type": "mainsite", "date": "20/08/2017"},
	{"id":1, "value": "row", "type": "mainsite", "date": "21/08/2017"},
	{"id":1, "value": "bench", "type": "mainsite", "date": "21/08/2017"},
	{"id":1, "value": "oh squat", "type": "mainsite", "date": "23/08/2017"},
	{"id":1, "value": "ring mu", "type": "mainsite", "date": "24/08/2017"},
	{"id":1, "value": "run", "type": "mainsite", "date": "24/08/2017"},
	{"id":1, "value": "burpee", "type": "mainsite", "date": "24/08/2017"},
	{"id":1, "value": "box jump", "type": "mainsite", "date": "24/08/2017"},
	{"id":1, "value": "pull up", "type": "mainsite", "date": "25/08/2017"},
	{"id":1, "value": "push up", "type": "mainsite", "date": "25/08/2017"},
	{"id":1, "value": "sit up", "type": "mainsite", "date": "25/08/2017"},
	{"id":1, "value": "squat", "type": "mainsite", "date": "25/08/2017"},
	{"id":1, "value": "box jump", "type": "mainsite", "date": "27/08/2017"},
	{"id":1, "value": "clean", "type": "mainsite", "date": "27/08/2017"},
	{"id":1, "value": "hs walk", "type": "mainsite", "date": "28/08/2017"},
	{"id":1, "value": "rope climb", "type": "mainsite", "date": "29/08/2017"},
	{"id":1, "value": "thruster", "type": "mainsite", "date": "29/08/2017"},
	{"id":1, "value": "ring dip", "type": "mainsite", "date": "29/08/2017"},
	{"id":1, "value": "oh squat", "type": "mainsite", "date": "29/08/2017"},
	{"id":1, "value": "sit up", "type": "mainsite", "date": "29/08/2017"},
	{"id":1, "value": "c2b", "type": "mainsite", "date": "31/08/2017"},
	{"id":1, "value": "burpee", "type": "mainsite", "date": "31/08/2017"},
	{"id":1, "value": "sdhp", "type": "mainsite", "date": "31/08/2017"},
	{"id":1, "value": "snatch", "type": "mainsite", "date": "01/09/2017"},
	{"id":1, "value": "swim", "type": "mainsite", "date": "02/09/2017"},
	{"id":1, "value": "push up", "type": "mainsite", "date": "02/09/2017"},
	{"id":1, "value": "squat", "type": "mainsite", "date": "04/09/2017"},
	{"id":1, "value": "db cluster", "type": "mainsite", "date": "05/09/2017"},
	{"id":1, "value": "pull up", "type": "mainsite", "date": "05/09/2017"},
	{"id":1, "value": "deadlift", "type": "mainsite", "date": "06/09/2017"},
	{"id":1, "value": "burpee", "type": "mainsite", "date": "06/09/2017"},
	{"id":1, "value": "bar mu", "type": "mainsite", "date": "06/09/2017"},
	{"id":1, "value": "farmer walk", "type": "mainsite", "date": "06/09/2017"},
	{"id":1, "value": "run", "type": "mainsite", "date": "08/09/2017"},
	{"id":1, "value": "row", "type": "mainsite", "date": "09/09/2017"},
	{"id":1, "value": "push jerk", "type": "mainsite", "date": "09/09/2017"},
	{"id":1, "value": "du", "type": "mainsite", "date": "10/09/2017"},
	{"id":1, "value": "pull up", "type": "mainsite", "date": "10/09/2017"},
	{"id":1, "value": "squat", "type": "mainsite", "date": "10/09/2017"},
	{"id":1, "value": "run", "type": "mainsite", "date": "10/09/2017"},
	{"id":1, "value": "hang power clean", "type": "mainsite", "date": "12/09/2017"},
	{"id":1, "value": "ghd", "type": "mainsite", "date": "13/09/2017"},
	{"id":1, "value": "ttb", "type": "mainsite", "date": "13/09/2017"},
	{"id":1, "value": "wall ball", "type": "mainsite", "date": "13/09/2017"},
	{"id":1, "value": "front squat", "type": "mainsite", "date": "14/09/2017"},
	{"id":1, "value": "hip extension", "type": "mainsite", "date": "16/09/2017"},
	{"id":1, "value": "rope climb", "type": "mainsite", "date": "16/09/2017"},
	{"id":1, "value": "squat", "type": "mainsite", "date": "17/09/2017"},
	{"id":1, "value": "push up", "type": "mainsite", "date": "17/09/2017"},
	{"id":1, "value": "lunge", "type": "mainsite", "date": "17/09/2017"},
	{"id":1, "value": "run", "type": "mainsite", "date": "17/09/2017"},
	{"id":1, "value": "L sit", "type": "mainsite", "date": "18/09/2017"},
	{"id":1, "value": "row", "type": "mainsite", "date": "18/09/2017"},
	{"id":1, "value": "oh squat", "type": "mainsite", "date": "20/09/2017"},
	{"id":1, "value": "snatch balance", "type": "mainsite", "date": "20/09/2017"},
	{"id":1, "value": "hang squat snatch", "type": "mainsite", "date": "20/09/2017"},
	{"id":1, "value": "thruster", "type": "mainsite", "date": "21/09/2017"},
	{"id":1, "value": "burpee", "type": "mainsite", "date": "21/09/2017"},
	{"id":1, "value": "du", "type": "mainsite", "date": "22/09/2017"},
	{"id":1, "value": "c2b", "type": "mainsite", "date": "22/09/2017"},
	{"id":1, "value": "hang power snatch", "type": "mainsite", "date": "22/09/2017"},
	{"id":1, "value": "wall ball", "type": "mainsite", "date": "24/09/2017"},
	{"id":1, "value": "clean", "type": "mainsite", "date": "24/09/2017"},
	{"id":1, "value": "row", "type": "mainsite", "date": "25/09/2017"},
	{"id":1, "value": "ttb", "type": "mainsite", "date": "25/09/2017"},
	{"id":1, "value": "thruster", "type": "mainsite", "date": "26/09/2017"},
	{"id":1, "value": "box jump", "type": "mainsite", "date": "26/09/2017"},
	{"id":1, "value": "deadlift", "type": "mainsite", "date": "26/09/2017"},
	{"id":1, "value": "run", "type": "mainsite", "date": "26/09/2017"},
	{"id":1, "value": "db snatch", "type": "mainsite", "date": "28/09/2017"},
	{"id":1, "value": "bar mu", "type": "mainsite", "date": "28/09/2017"},
	{"id":1, "value": "hspu", "type": "mainsite", "date": "29/09/2017"},
	{"id":1, "value": "du", "type": "mainsite", "date": "29/09/2017"},
	{"id":1, "value": "back squat", "type": "mainsite", "date": "29/09/2017"},
	{"id":1, "value": "row", "type": "mainsite", "date": "30/09/2017"},
	{"id":1, "value": "thruster", "type": "mainsite", "date": "30/09/2017"},
	{"id":1, "value": "c2b", "type": "mainsite", "date": "30/09/2017"},
	{"id":1, "value": "burpee", "type": "mainsite", "date": "02/10/2017"},
	{"id":1, "value": "box jump", "type": "mainsite", "date": "02/10/2017"},
	{"id":1, "value": "deadlift", "type": "mainsite", "date": "02/10/2017"},
	{"id":1, "value": "run", "type": "mainsite", "date": "03/10/2017"},
	{"id":1, "value": "bike", "type": "mainsite", "date": "04/10/2017"},
	{"id":1, "value": "push up", "type": "mainsite", "date": "04/10/2017"},
	{"id":1, "value": "pistol squat", "type": "mainsite", "date": "04/10/2017"},
	{"id":1, "value": "power clean", "type": "mainsite", "date": "06/10/2017"},
	{"id":1, "value": "thruster", "type": "mainsite", "date": "06/10/2017"},
	{"id":1, "value": "hs walk", "type": "mainsite", "date": "07/10/2017"},
	{"id":1, "value": "broad jump", "type": "mainsite", "date": "07/10/2017"},
	{"id":1, "value": "lunge", "type": "mainsite", "date": "07/10/2017"},
	{"id":1, "value": "wall ball", "type": "mainsite", "date": "08/10/2017"},
	{"id":1, "value": "sdhp", "type": "mainsite", "date": "08/10/2017"},
	{"id":1, "value": "box jump", "type": "mainsite", "date": "08/10/2017"},
	{"id":1, "value": "push press", "type": "mainsite", "date": "08/10/2017"},
	{"id":1, "value": "row", "type": "mainsite", "date": "08/10/2017"},
	{"id":1, "value": "oh squat", "type": "mainsite", "date": "10/10/2017"},
	{"id":1, "value": "run", "type": "mainsite", "date": "11/10/2017"},
	{"id":1, "value": "pull up", "type": "mainsite", "date": "11/10/2017"},
	{"id":1, "value": "c&j", "type": "mainsite", "date": "11/10/2017"},
	{"id":1, "value": "kb swing", "type": "mainsite", "date": "12/10/2017"},
	{"id":1, "value": "ghd", "type": "mainsite", "date": "12/10/2017"},
	{"id":1, "value": "back extension", "type": "mainsite", "date": "12/10/2017"},
	{"id":1, "value": "kte", "type": "mainsite", "date": "12/10/2017"},
	{"id":1, "value": "pistol squat", "type": "mainsite", "date": "14/10/2017"},
	{"id":1, "value": "wall ball", "type": "mainsite", "date": "14/10/2017"},
	{"id":1, "value": "box jump", "type": "mainsite", "date": "14/10/2017"},
	{"id":1, "value": "deadlift", "type": "mainsite", "date": "14/10/2017"},
	{"id":1, "value": "power clean", "type": "mainsite", "date": "14/10/2017"},
	{"id":1, "value": "front squat", "type": "mainsite", "date": "14/10/2017"},
	{"id":1, "value": "L rope climb", "type": "mainsite", "date": "15/10/2017"},
	{"id":1, "value": "legless rope climb", "type": "mainsite", "date": "15/10/2017"},
	{"id":1, "value": "rope climb", "type": "mainsite", "date": "15/10/2017"},
	{"id":1, "value": "burpee", "type": "mainsite", "date": "16/10/2017"},
	{"id":1, "value": "row", "type": "mainsite", "date": "16/10/2017"},
	{"id":1, "value": "push up", "type": "mainsite", "date": "18/10/2017"},
	{"id":1, "value": "ring dip", "type": "mainsite", "date": "18/10/2017"},
	{"id":1, "value": "hspu", "type": "mainsite", "date": "18/10/2017"},
	{"id":1, "value": "bench", "type": "mainsite", "date": "18/10/2017"},
	{"id":1, "value": "push jerk", "type": "mainsite", "date": "18/10/2017"},
	{"id":1, "value": "push press", "type": "mainsite", "date": "18/10/2017"},
	{"id":1, "value": "back squat", "type": "mainsite", "date": "19/10/2017"},
	{"id":1, "value": "db lunge", "type": "mainsite", "date": "20/10/2017"},
	{"id":1, "value": "run", "type": "mainsite", "date": "20/10/2017"},
	{"id":1, "value": "sit up", "type": "mainsite", "date": "22/10/2017"},
	{"id":1, "value": "ttb", "type": "mainsite", "date": "22/10/2017"},
	{"id":1, "value": "ghd", "type": "mainsite", "date": "22/10/2017"},
	{"id":1, "value": "pull up", "type": "mainsite", "date": "22/10/2017"},
	{"id":1, "value": "bar mu", "type": "mainsite", "date": "22/10/2017"},
	{"id":1, "value": "power clean", "type": "mainsite", "date": "23/10/2017"},
	{"id":1, "value": "run", "type": "mainsite", "date": "24/10/2017"},
	{"id":1, "value": "farmer walk", "type": "mainsite", "date": "24/10/2017"},
	{"id":1, "value": "sdhp", "type": "mainsite", "date": "26/10/2017"},
	{"id":1, "value": "hspu", "type": "mainsite", "date": "26/10/2017"},
	{"id":1, "value": "front squat", "type": "mainsite", "date": "27/10/2017"},
	{"id":1, "value": "run", "type": "mainsite", "date": "28/10/2017"},
	{"id":1, "value": "du", "type": "mainsite", "date": "28/10/2017"},
	{"id":1, "value": "db push jerk", "type": "mainsite", "date": "28/10/2017"},
	{"id":1, "value": "pull up", "type": "mainsite", "date": "28/10/2017"},
	{"id":1, "value": "db hang squat clean", "type": "mainsite", "date": "28/10/2017"},
	{"id":1, "value": "thruster", "type": "mainsite", "date": "30/10/2017"},
	{"id":1, "value": "push press", "type": "mainsite", "date": "30/10/2017"},
	{"id":1, "value": "push jerk", "type": "mainsite", "date": "30/10/2017"},
	{"id":1, "value": "split jerk", "type": "mainsite", "date": "30/10/2017"},
	{"id":1, "value": "row", "type": "mainsite", "date": "31/10/2017"},
	{"id":1, "value": "ghd", "type": "mainsite", "date": "31/10/2017"},
	{"id":1, "value": "squat snatch", "type": "mainsite", "date": "01/11/2017"},
	{"id":1, "value": "burpee", "type": "mainsite", "date": "01/11/2017"},
	{"id":1, "value": "row", "type": "mainsite", "date": "03/11/2017"},
	{"id":1, "value": "dip", "type": "mainsite", "date": "03/11/2017"},
	{"id":1, "value": "turkish get up", "type": "mainsite", "date": "03/11/2017"},
	{"id":1, "value": "deadlift", "type": "mainsite", "date": "04/11/2017"},
	{"id":1, "value": "oh squat", "type": "mainsite", "date": "05/11/2017"},
	{"id":1, "value": "ring mu", "type": "mainsite", "date": "05/11/2017"},
	{"id":1, "value": "L sit", "type": "mainsite", "date": "07/11/2017"},
	{"id":1, "value": "ring row", "type": "mainsite", "date": "07/11/2017"},
	{"id":1, "value": "hs hold", "type": "mainsite", "date": "07/11/2017"},
	{"id":1, "value": "row", "type": "mainsite", "date": "07/11/2017"},
	{"id":1, "value": "split jerk", "type": "mainsite", "date": "08/11/2017"},
	{"id":1, "value": "db thruster", "type": "mainsite", "date": "09/11/2017"},
	{"id":1, "value": "du", "type": "mainsite", "date": "09/11/2017"},
	{"id":1, "value": "rope climb", "type": "mainsite", "date": "09/11/2017"},
	{"id":1, "value": "run", "type": "mainsite", "date": "11/11/2017"},
	{"id":1, "value": "power snatch", "type": "mainsite", "date": "11/11/2017"},
	{"id":1, "value": "pull up", "type": "mainsite", "date": "11/11/2017"},
	{"id":1, "value": "power clean", "type": "mainsite", "date": "11/11/2017"},
	{"id":1, "value": "wall ball", "type": "mainsite", "date": "12/11/2017"},
	{"id":1, "value": "ghd", "type": "mainsite", "date": "12/11/2017"},
	{"id":1, "value": "bar hang", "type": "mainsite", "date": "13/11/2017"},
	{"id":1, "value": "run", "type": "mainsite", "date": "13/11/2017"},
	{"id":1, "value": "push up", "type": "mainsite", "date": "13/11/2017"},
	{"id":1, "value": "deadlift", "type": "mainsite", "date": "15/11/2017"},
	{"id":1, "value": "row", "type": "mainsite", "date": "16/11/2017"},
	{"id":1, "value": "push press", "type": "mainsite", "date": "16/11/2017"},
	{"id":1, "value": "ghd", "type": "mainsite", "date": "16/11/2017"},
	{"id":1, "value": "thruster", "type": "mainsite", "date": "17/11/2017"},
	{"id":1, "value": "pull up", "type": "mainsite", "date": "17/11/2017"},
	{"id":1, "value": "run", "type": "mainsite", "date": "19/11/2017"},
	{"id":1, "value": "run backwards", "type": "mainsite", "date": "19/11/2017"},
	{"id":1, "value": "c&j", "type": "mainsite", "date": "20/11/2017"},
	{"id":1, "value": "squat", "type": "mainsite", "date": "21/11/2017"},
	{"id":1, "value": "ring hspu", "type": "mainsite", "date": "21/11/2017"},
	{"id":1, "value": "L pull up", "type": "mainsite", "date": "21/11/2017"},
	{"id":1, "value": "run", "type": "mainsite", "date": "23/11/2017"},
	{"id":1, "value": "burpee", "type": "mainsite", "date": "23/11/2017"},
	{"id":1, "value": "kb swing", "type": "mainsite", "date": "24/11/2017"},
	{"id":1, "value": "sit up", "type": "mainsite", "date": "24/11/2017"},
	{"id":1, "value": "snatch", "type": "mainsite", "date": "25/11/2017"},
	{"id":1, "value": "c&j", "type": "mainsite", "date": "25/11/2017"},
	{"id":1, "value": "lunge", "type": "mainsite", "date": "27/11/2017"},
	{"id":1, "value": "squat", "type": "mainsite", "date": "27/11/2017"},
	{"id":1, "value": "hip extension", "type": "mainsite", "date": "27/11/2017"},
	{"id":1, "value": "run", "type": "mainsite", "date": "28/11/2017"},
	{"id":1, "value": "power snatch", "type": "mainsite", "date": "28/11/2017"},
	{"id":1, "value": "bar mu", "type": "mainsite", "date": "28/11/2017"},
	{"id":1, "value": "du", "type": "mainsite", "date": "29/11/2017"},
	{"id":1, "value": "sit up", "type": "mainsite", "date": "29/11/2017"},
	{"id":1, "value": "snatch", "type": "mainsite", "date": "01/12/2017"},
	{"id":1, "value": "pull up", "type": "mainsite", "date": "02/12/2017"},
	{"id":1, "value": "row", "type": "mainsite", "date": "02/12/2017"},
	{"id":1, "value": "oh squat", "type": "mainsite", "date": "02/12/2017"},
	{"id":1, "value": "box jump", "type": "mainsite", "date": "02/12/2017"},
	{"id":1, "value": "c&j", "type": "mainsite", "date": "03/12/2017"},
	{"id":1, "value": "hs walk", "type": "mainsite", "date": "05/12/2017"},
	{"id":1, "value": "burpee", "type": "mainsite", "date": "05/12/2017"},
	{"id":1, "value": "pistol squat", "type": "mainsite", "date": "05/12/2017"},
	{"id":1, "value": "run", "type": "mainsite", "date": "06/12/2017"},
	{"id":1, "value": "push press", "type": "mainsite", "date": "06/12/2017"},
	{"id":1, "value": "c2b", "type": "mainsite", "date": "06/12/2017"},
	{"id":1, "value": "squat", "type": "mainsite", "date": "07/12/2017"},
	{"id":1, "value": "strict press", "type": "mainsite", "date": "07/12/2017"},
	{"id":1, "value": "deadlift", "type": "mainsite", "date": "07/12/2017"},
	{"id":1, "value": "wall ball", "type": "mainsite", "date": "09/12/2017"},
	{"id":1, "value": "pull up", "type": "mainsite", "date": "09/12/2017"},
	{"id":1, "value": "ttb", "type": "mainsite", "date": "10/12/2017"},
	{"id":1, "value": "dip", "type": "mainsite", "date": "10/12/2017"},
	{"id":1, "value": "deadlift", "type": "mainsite", "date": "10/12/2017"},
	{"id":1, "value": "hspu", "type": "mainsite", "date": "10/12/2017"},
	{"id":1, "value": "row", "type": "mainsite", "date": "11/12/2017"},
	{"id":1, "value": "oh squat", "type": "mainsite", "date": "11/12/2017"},
	{"id":1, "value": "front squat", "type": "mainsite", "date": "13/12/2017"},
	{"id":1, "value": "ring mu", "type": "mainsite", "date": "14/12/2017"},
	{"id":1, "value": "run", "type": "mainsite", "date": "14/12/2017"},
	{"id":1, "value": "squat clean", "type": "mainsite", "date": "15/12/2017"},
	{"id":1, "value": "push jerk", "type": "mainsite", "date": "15/12/2017"},
	{"id":1, "value": "run", "type": "mainsite", "date": "17/12/2017"},
	{"id":1, "value": "back squat", "type": "mainsite", "date": "18/12/2017"},
	{"id":1, "value": "rope climb", "type": "mainsite", "date": "18/12/2017"},
	{"id":1, "value": "run", "type": "mainsite", "date": "19/12/2017"},
	{"id":1, "value": "deadlift", "type": "mainsite", "date": "19/12/2017"},
	{"id":1, "value": "hspu", "type": "mainsite", "date": "19/12/2017"},
	{"id":1, "value": "box jump", "type": "mainsite", "date": "21/12/2017"},
	{"id":1, "value": "db oh squat", "type": "mainsite", "date": "21/12/2017"},
	{"id":1, "value": "ghd", "type": "mainsite", "date": "21/12/2017"},
	{"id":1, "value": "row", "type": "mainsite", "date": "22/12/2017"},
	{"id":1, "value": "db thruster", "type": "mainsite", "date": "22/12/2017"},
	{"id":1, "value": "c2b", "type": "mainsite", "date": "22/12/2017"},
	{"id":1, "value": "clean", "type": "mainsite", "date": "23/12/2017"},
	{"id":1, "value": "bench", "type": "mainsite", "date": "23/12/2017"},
	{"id":1, "value": "oh squat", "type": "mainsite", "date": "23/12/2017"},
	{"id":1, "value": "run", "type": "mainsite", "date": "25/12/2017"},
	{"id":1, "value": "squat", "type": "mainsite", "date": "25/12/2017"},
	{"id":1, "value": "kb snatch", "type": "mainsite", "date": "26/12/2017"},
	{"id":1, "value": "sit up", "type": "mainsite", "date": "26/12/2017"},
	{"id":1, "value": "lunge", "type": "mainsite", "date": "26/12/2017"},
	{"id":1, "value": "squat clean", "type": "mainsite", "date": "27/12/2017"},
	{"id":1, "value": "push jerk", "type": "mainsite", "date": "27/12/2017"},
	{"id":1, "value": "burpee", "type": "mainsite", "date": "27/12/2017"},
	{"id":1, "value": "c2b", "type": "mainsite", "date": "27/12/2017"},
	{"id":1, "value": "squat", "type": "mainsite", "date": "29/12/2017"},
	{"id":1, "value": "kte", "type": "mainsite", "date": "29/12/2017"},
	{"id":1, "value": "ring push up", "type": "mainsite", "date": "29/12/2017"},
	{"id":1, "value": "squat snatch", "type": "mainsite", "date": "30/12/2017"},
	{"id":1, "value": "c&j", "type": "mainsite", "date": "30/12/2017"},
	{"id":1, "value": "du", "type": "mainsite", "date": "30/12/2017"},
	{"id":1, "value": "c2b", "type": "mainsite", "date": "31/12/2017"},
	{"id":1, "value": "dip", "type": "mainsite", "date": "31/12/2017"},
	{"id":1, "value": "run", "type": "mainsite", "date": "31/12/2017"},
	{"id":1, "value": "pull up", "type": "mainsite", "date": "02/01/2018"},
	{"id":1, "value": "push up", "type": "mainsite", "date": "02/01/2018"},
	{"id":1, "value": "sit up", "type": "mainsite", "date": "02/01/2018"},
	{"id":1, "value": "squat", "type": "mainsite", "date": "02/01/2018"},
	{"id":1, "value": "squat", "type": "mainsite", "date": "03/01/2018"},
	{"id":1, "value": "strict press", "type": "mainsite", "date": "03/01/2018"},
	{"id":1, "value": "deadlift", "type": "mainsite", "date": "03/01/2018"},
	{"id":1, "value": "pistol squat", "type": "mainsite", "date": "04/01/2018"},
	{"id":1, "value": "hs walk", "type": "mainsite", "date": "04/01/2018"},
	{"id":1, "value": "run", "type": "mainsite", "date": "06/01/2018"},
	{"id":1, "value": "L pull up", "type": "mainsite", "date": "06/01/2018"},
	{"id":1, "value": "c&j", "type": "mainsite", "date": "06/01/2018"},
	{"id":1, "value": "row", "type": "mainsite", "date": "07/01/2018"},
	{"id":1, "value": "front squat", "type": "mainsite", "date": "08/01/2018"},
	{"id":1, "value": "thruster", "type": "mainsite", "date": "08/01/2018"},
	{"id":1, "value": "push jerk", "type": "mainsite", "date": "08/01/2018"},
	{"id":1, "value": "power snatch", "type": "mainsite", "date": "10/01/2018"},
	{"id":1, "value": "oh lunge", "type": "mainsite", "date": "10/01/2018"},
	{"id":1, "value": "rope climb", "type": "mainsite", "date": "10/01/2018"},
	{"id":1, "value": "deadlift", "type": "mainsite", "date": "11/01/2018"},
	{"id":1, "value": "box jump", "type": "mainsite", "date": "11/01/2018"},
	{"id":1, "value": "med ball clean", "type": "mainsite", "date": "12/01/2018"},
	{"id":1, "value": "du", "type": "mainsite", "date": "12/01/2018"},
	{"id":1, "value": "oh squat", "type": "mainsite", "date": "14/01/2018"},
	{"id":1, "value": "ring mu", "type": "mainsite", "date": "15/01/2018"},
	{"id":1, "value": "thruster", "type": "mainsite", "date": "15/01/2018"},
	{"id":1, "value": "row", "type": "mainsite", "date": "15/01/2018"},
	{"id":1, "value": "run", "type": "mainsite", "date": "16/01/2018"},
	{"id":1, "value": "kb swing", "type": "mainsite", "date": "16/01/2018"},
	{"id":1, "value": "pull up", "type": "mainsite", "date": "16/01/2018"},
	{"id":1, "value": "push press", "type": "mainsite", "date": "18/01/2018"},
	{"id":1, "value": "power clean", "type": "mainsite", "date": "18/01/2018"},
	{"id":1, "value": "db snatch", "type": "mainsite", "date": "19/01/2018"},
	{"id":1, "value": "burpee", "type": "mainsite", "date": "19/01/2018"},
	{"id":1, "value": "row", "type": "mainsite", "date": "20/01/2018"},
	{"id":1, "value": "hspu", "type": "mainsite", "date": "20/01/2018"},
	{"id":1, "value": "rope climb", "type": "mainsite", "date": "20/01/2018"},
	{"id":1, "value": "deficit deadlift", "type": "mainsite", "date": "22/01/2018"},
	{"id":1, "value": "hang squat clean", "type": "mainsite", "date": "23/01/2018"},
	{"id":1, "value": "burpee", "type": "mainsite", "date": "23/01/2018"},
	{"id":1, "value": "bar mu", "type": "mainsite", "date": "23/01/2018"},
	{"id":1, "value": "run", "type": "mainsite", "date": "24/01/2018"},
	{"id":1, "value": "sit up", "type": "mainsite", "date": "24/01/2018"},
	{"id":1, "value": "squat", "type": "mainsite", "date": "26/01/2018"},
	{"id":1, "value": "c2b", "type": "mainsite", "date": "27/01/2018"},
	{"id":1, "value": "push up", "type": "mainsite", "date": "27/01/2018"},
	{"id":1, "value": "pistol squat", "type": "mainsite", "date": "27/01/2018"},
	{"id":1, "value": "run", "type": "mainsite", "date": "27/01/2018"},
	{"id":1, "value": "snatch", "type": "mainsite", "date": "28/01/2018"},
	{"id":1, "value": "box jump", "type": "mainsite", "date": "28/01/2018"},
	{"id":1, "value": "db deadlift", "type": "mainsite", "date": "30/01/2018"},
	{"id":1, "value": "db strict press", "type": "mainsite", "date": "30/01/2018"},
	{"id":1, "value": "oh lunge", "type": "mainsite", "date": "31/01/2018"},
	{"id":1, "value": "kte", "type": "mainsite", "date": "31/01/2018"},
	{"id":1, "value": "sit up", "type": "mainsite", "date": "31/01/2018"},
	{"id":1, "value": "row", "type": "mainsite", "date": "31/01/2018"}
]